mailworks/__init__.py
mailworks/config.py
mailworks/exceptions.py
mailworks/mail_sender.py
mailworks-2.2.0.dist-info/licenses/LICENSE
mailworks-2.2.0.dist-info/METADATA
mailworks-2.2.0.dist-info/WHEEL
mailworks-2.2.0.dist-info/top_level.txt
mailworks-2.2.0.dist-info/RECORD
