Metadata-Version: 2.4
Name: mailworks
Version: 2.2.0
Summary: A Python package for sending emails using any SMTP server with STARTTLS support
Home-page: https://github.com/antoniocostabr/mailworks
Author: Antonio Costa
Author-email: Antonio Costa <antoniocostabr@gmail.com>
License-Expression: MIT
Project-URL: Homepage, https://github.com/antoniocostabr/mailworks
Project-URL: Repository, https://github.com/antoniocostabr/mailworks
Project-URL: Bug Reports, https://github.com/antoniocostabr/mailworks/issues
Project-URL: Documentation, https://github.com/antoniocostabr/mailworks#readme
Keywords: email,smtp,send,mail,starttls,python,gmail,outlook,corporate,universal
Classifier: Development Status :: 4 - Beta
Classifier: Intended Audience :: Developers
Classifier: Topic :: Communications :: Email
Classifier: Programming Language :: Python :: 3
Classifier: Programming Language :: Python :: 3.7
Classifier: Programming Language :: Python :: 3.8
Classifier: Programming Language :: Python :: 3.9
Classifier: Programming Language :: Python :: 3.10
Classifier: Programming Language :: Python :: 3.11
Classifier: Operating System :: OS Independent
Requires-Python: >=3.7
License-File: LICENSE
Provides-Extra: dev
Requires-Dist: pytest>=7.0.0; extra == "dev"
Requires-Dist: black>=22.0.0; extra == "dev"
Requires-Dist: flake8>=4.0.0; extra == "dev"
Requires-Dist: mypy>=0.950; extra == "dev"
Dynamic: author
Dynamic: home-page
Dynamic: license-file
Dynamic: requires-python
